mcp_utils/__init__.py
mcp_utils/core.py
mcp_utils/queue.py
mcp_utils/schema.py
mcp_utils/utils.py
mcp_utils_msgspec-2.1.0.dist-info/licenses/LICENSE
mcp_utils_msgspec-2.1.0.dist-info/METADATA
mcp_utils_msgspec-2.1.0.dist-info/WHEEL
mcp_utils_msgspec-2.1.0.dist-info/top_level.txt
mcp_utils_msgspec-2.1.0.dist-info/RECORD
