Metadata-Version: 2.4
Name: mcp-utils-msgspec
Version: 2.1.0
Summary: Synchronous utilities for Model Context Protocol (MCP) integration
Author: Fulfil.IO Inc, Pioreactor Inc.
License-Expression: MIT
Project-URL: Homepage, https://github.com/pioreactor/mcp-utils
Project-URL: Repository, https://github.com/pioreactor/mcp-utils.git
Keywords: mcp,model-context-protocol,ai,llm
Requires-Python: >=3.10
License-File: LICENSE
Requires-Dist: msgspec>=0.18.0
Provides-Extra: dev
Requires-Dist: pytest>=8.0.0; extra == "dev"
Dynamic: license-file
